multiadbconnect/README.MD
multiadbconnect/__init__.py
multiadbconnect/requirements.txt
multiadbconnect/thirdparty.json
multiadbconnect-0.10.dist-info/LICENSE.rst
multiadbconnect-0.10.dist-info/METADATA
multiadbconnect-0.10.dist-info/WHEEL
multiadbconnect-0.10.dist-info/top_level.txt
multiadbconnect-0.10.dist-info/RECORD
