Metadata-Version: 2.1
Name: multiadbconnect
Version: 0.10
Summary: Establish a adb connection to different emulators at the same time (Bluestacks, MEmu, MuMu, LdPlayer ...) - Windows only
Home-page: https://github.com/hansalemaos/multiadbconnect
Author: Johannes Fischer
Author-email: aulasparticularesdealemaosp@gmail.com
License: MIT
Keywords: adb,connect
Classifier: Development Status :: 4 - Beta
Classifier: Programming Language :: Python :: 3 :: Only
Classifier: Programming Language :: Python :: 3.10
Classifier: Topic :: Software Development :: Libraries :: Python Modules
Classifier: Topic :: Utilities
License-File: LICENSE.rst
Requires-Dist: a-pandas-ex-apply-ignore-exceptions
Requires-Dist: numpy
Requires-Dist: pandas
Requires-Dist: psutil
Requires-Dist: shortpath83
Requires-Dist: subprocess-alive
